ntuee_mailer/AutoMailer.py
ntuee_mailer/Letter.py
ntuee_mailer/__init__.py
ntuee_mailer/__main__.py
ntuee_mailer/config-default.ini
ntuee_mailer/globals.py
ntuee_mailer/main.py
ntuee_mailer/template_letter/attachments/.placeholder
ntuee_mailer/template_letter/config.yml
ntuee_mailer/template_letter/content.html
ntuee_mailer/template_letter/recipients.csv
ntuee_mailer/utils.py
ntuee_mailer-2.0.15.dist-info/LICENSE
ntuee_mailer-2.0.15.dist-info/METADATA
ntuee_mailer-2.0.15.dist-info/WHEEL
ntuee_mailer-2.0.15.dist-info/entry_points.txt
ntuee_mailer-2.0.15.dist-info/RECORD
