Metadata-Version: 2.1
Name: ntuee-mailer
Version: 2.0.15
Summary: an auto mailer to send emails in batch for you
Home-page: https://github.com/madmaxieee/ntuee-mailer
License: MIT
Author: madmaxieee
Author-email: 76544194+madmaxieee@users.noreply.github.com
Requires-Python: >=3.6.3,<4.0.0
Classifier: License :: OSI Approved :: MIT License
Classifier: Programming Language :: Python :: 3
Classifier: Programming Language :: Python :: 3.7
Classifier: Programming Language :: Python :: 3.8
Classifier: Programming Language :: Python :: 3.9
Classifier: Programming Language :: Python :: 3.10
Classifier: Programming Language :: Python :: 3.11
Classifier: Programming Language :: Python :: 3.12
Requires-Dist: Cerberus (==1.3.4)
Requires-Dist: PyYAML (==6.0)
Requires-Dist: click (==8.0.4)
Requires-Dist: email-validator (==1.2.1)
Requires-Dist: rich (==12.5.1)
Requires-Dist: typer[all] (>=0.6.1,<0.7.0)
Project-URL: Repository, https://github.com/madmaxieee/ntuee-mailer
